{"results": [{"canCode": "89756", "bName": "CAYETANO, ALAN PETER (IND)", "percentage": "50.59", "votes": "9,542"}, {"canCode": "89755", "bName": "ESCUDERO, CHIZ (IND)", "percentage": "8.88", "votes": "1,675"}, {"canCode": "89751", "bName": "HONASAN, GRINGO (UNA)", "percentage": "1.21", "votes": "230"}, {"canCode": "89752", "bName": "MARCOS, BONGBONG (IND)", "percentage": "23.44", "votes": "4,422"}, {"canCode": "89754", "bName": "ROBREDO, LENI DAANG MATUWID (LP)", "percentage": "14.89", "votes": "2,809"}, {"canCode": "89753", "bName": "TRILLANES, ANTONIO IV (IND)", "percentage": "0.97", "votes": "183"}], "code": "11162", "stats": {"transmission": "100.00", "ballots": {"rows": [{"value": "20,806", "label": "ballots.total"}]}, "regionInfo": {"rows": [{"value": "39", "label": "tally.total.4"}, {"value": "39", "label": "tally.reported.4"}]}, "voters": {"rows": [{"value": "25,750", "label": "voters.registered"}, {"value": "80.80%", "label": "voters.turn.out"}]}}, "name": "VICE-PRESIDENT PHILIPPINES", "cClass": "2"}