{"results": [{"canCode": "123622", "bName": "ABIOG, RAFAEL (UNA)", "percentage": "6.25", "votes": "2,445"}, {"canCode": "123618", "bName": "ARQUE, MELECIO JR. (PPP)", "percentage": "7.28", "votes": "2,847"}, {"canCode": "123625", "bName": "ARZAGA,  JOAQUIN (UNA)", "percentage": "5.10", "votes": "1,995"}, {"canCode": "123628", "bName": "BAGUINBIN, NICANOR (UNA)", "percentage": "2.87", "votes": "1,122"}, {"canCode": "123615", "bName": "BATIANCILA, ELVIN (PPP)", "percentage": "7.33", "votes": "2,867"}, {"canCode": "123611", "bName": "CORONIA, ADOLFO (IND)", "percentage": "0.18", "votes": "71"}, {"canCode": "123621", "bName": "DACULAP, ANTONIO (IND)", "percentage": "8.61", "votes": "3,367"}, {"canCode": "123616", "bName": "DADAYA, EDWIN (PPP)", "percentage": "3.11", "votes": "1,217"}, {"canCode": "123623", "bName": "DARAS, LIMUEL (UNA)", "percentage": "5.24", "votes": "2,049"}, {"canCode": "123630", "bName": "DUSONG, PANSING (IND)", "percentage": "3.50", "votes": "1,369"}, {"canCode": "123617", "bName": "GADIANO, REYMOND (PPP)", "percentage": "7.12", "votes": "2,782"}, {"canCode": "123629", "bName": "GOROSIN, JOCELYN (UNA)", "percentage": "3.61", "votes": "1,414"}, {"canCode": "123619", "bName": "GUAYCO, NOEL (PPP)", "percentage": "7.18", "votes": "2,807"}, {"canCode": "123613", "bName": "MANONGSONG, LITO (PPP)", "percentage": "4.56", "votes": "1,784"}, {"canCode": "123610", "bName": "MARAVILLA, JAIME (IND)", "percentage": "2.42", "votes": "946"}, {"canCode": "123612", "bName": "MIRALES, CONNIE (IND)", "percentage": "5.56", "votes": "2,173"}, {"canCode": "123627", "bName": "NAMIA, JOSEPHINE (UNA)", "percentage": "5.88", "votes": "2,298"}, {"canCode": "123624", "bName": "PALANCA, REX (UNA)", "percentage": "1.52", "votes": "595"}, {"canCode": "123620", "bName": "PANTINOPLE, PALE (PPP)", "percentage": "4.87", "votes": "1,906"}, {"canCode": "123614", "bName": "PE, JUANCHO (PPP)", "percentage": "4.75", "votes": "1,857"}, {"canCode": "123626", "bName": "RONDINA, EDWIN (UNA)", "percentage": "2.94", "votes": "1,152"}], "code": "16129", "stats": {"transmission": "100.00", "ballots": {"rows": [{"value": "6,668", "label": "ballots.total"}]}, "regionInfo": {"rows": [{"value": "17", "label": "tally.total.4"}, {"value": "17", "label": "tally.reported.4"}]}, "voters": {"rows": [{"value": "8,030", "label": "voters.registered"}, {"value": "83.03%", "label": "voters.turn.out"}]}}, "name": "MEMBER, SANGGUNIANG BAYAN PALAWAN - ARACELI  - LONE DIST", "cClass": "24"}