{"name": "SUMILAO", "level": 4, "url": "data/regions/1319.json", "sitePath": "0/10/1300/1319", "isFinalLevel": false, "subRegions": {"1319010": {"categoryName": "Barangay", "parentCustomCode": "1319", "level": 5, "url": "data/regions/1319010.json", "parentName": "SUMILAO", "isFinalLevel": true, "parentCategoryName": "City/Municipality", "customCode": "1319010", "name": "VISTA VILLA"}, "1319009": {"categoryName": "Barangay", "parentCustomCode": "1319", "level": 5, "url": "data/regions/1319009.json", "parentName": "SUMILAO", "isFinalLevel": true, "parentCategoryName": "City/Municipality", "customCode": "1319009", "name": "POBLACION"}, "1319008": {"categoryName": "Barangay", "parentCustomCode": "1319", "level": 5, "url": "data/regions/1319008.json", "parentName": "SUMILAO", "isFinalLevel": true, "parentCategoryName": "City/Municipality", "customCode": "1319008", "name": "SAN VICENTE"}, "1319001": {"categoryName": "Barangay", "parentCustomCode": "1319", "level": 5, "url": "data/regions/1319001.json", "parentName": "SUMILAO", "isFinalLevel": true, "parentCategoryName": "City/Municipality", "customCode": "1319001", "name": "KISOLON"}, "1319003": {"categoryName": "Barangay", "parentCustomCode": "1319", "level": 5, "url": "data/regions/1319003.json", "parentName": "SUMILAO", "isFinalLevel": true, "parentCategoryName": "City/Municipality", "customCode": "1319003", "name": "LICOAN"}, "1319002": {"categoryName": "Barangay", "parentCustomCode": "1319", "level": 5, "url": "data/regions/1319002.json", "parentName": "SUMILAO", "isFinalLevel": true, "parentCategoryName": "City/Municipality", "customCode": "1319002", "name": "CULASI"}, "1319005": {"categoryName": "Barangay", "parentCustomCode": "1319", "level": 5, "url": "data/regions/1319005.json", "parentName": "SUMILAO", "isFinalLevel": true, "parentCategoryName": "City/Municipality", "customCode": "1319005", "name": "OCASION"}, "1319004": {"categoryName": "Barangay", "parentCustomCode": "1319", "level": 5, "url": "data/regions/1319004.json", "parentName": "SUMILAO", "isFinalLevel": true, "parentCategoryName": "City/Municipality", "customCode": "1319004", "name": "LUPIAGAN"}, "1319007": {"categoryName": "Barangay", "parentCustomCode": "1319", "level": 5, "url": "data/regions/1319007.json", "parentName": "SUMILAO", "isFinalLevel": true, "parentCategoryName": "City/Municipality", "customCode": "1319007", "name": "SAN ROQUE"}, "1319006": {"categoryName": "Barangay", "parentCustomCode": "1319", "level": 5, "url": "data/regions/1319006.json", "parentName": "SUMILAO", "isFinalLevel": true, "parentCategoryName": "City/Municipality", "customCode": "1319006", "name": "PUNTIAN"}}, "parentRegionCC": "1300", "contests": [{"url": "tallies/288/288579/11161.json", "code": "11161", "customCode": "00199009", "cClass": "1"}, {"url": "tallies/288/288579/11162.json", "code": "11162", "customCode": "00299009", "cClass": "2"}, {"url": "tallies/288/288579/11163.json", "code": "11163", "customCode": "00399009", "cClass": "3"}, {"url": "tallies/288/288579/11164.json", "code": "11164", "customCode": "01199009", "cClass": "4"}, {"url": "tallies/288/288579/11190.json", "code": "11190", "customCode": "00713001", "cClass": "5"}, {"url": "tallies/288/288579/11425.json", "code": "11425", "customCode": "00413009", "cClass": "9"}, {"url": "tallies/288/288579/11506.json", "code": "11506", "customCode": "00513009", "cClass": "10"}, {"url": "tallies/288/288579/11586.json", "code": "11586", "customCode": "00613001", "cClass": "12"}, {"url": "tallies/288/288579/12044.json", "code": "12044", "customCode": "00813199", "cClass": "18"}, {"url": "tallies/288/288579/13678.json", "code": "13678", "customCode": "00913199", "cClass": "19"}, {"url": "tallies/288/288579/15341.json", "code": "15341", "customCode": "01013199", "cClass": "24"}], "customCode": "1319", "categoryName": "City/Municipality"}