{"results": [{"canCode": "95599", "bName": "FELICIANO, JEAN (LP)", "percentage": "54.01", "votes": "15,821"}, {"canCode": "95600", "bName": "LEONCIO, BOYET (IND)", "percentage": "45.98", "votes": "13,471"}], "code": "12923", "stats": {"transmission": "98.30", "ballots": {"rows": [{"value": "30,735", "label": "ballots.total"}]}, "regionInfo": {"rows": [{"value": "59", "label": "tally.total.4"}, {"value": "58", "label": "tally.reported.4"}]}, "voters": {"rows": [{"value": "35,663", "label": "voters.registered"}, {"value": "86.18%", "label": "voters.turn.out"}]}}, "name": "MAYOR PALAWAN - BROOKES POINT", "cClass": "18"}