{"results": [{"canCode": "125134", "bName": "ACEDERA, MINERVA (NPC)", "percentage": "8.43", "votes": "9,257"}, {"canCode": "125145", "bName": "AGUSTIN, PABLO (KBL)", "percentage": "4.21", "votes": "4,629"}, {"canCode": "125132", "bName": "AQUINO, JIMMY (NPC)", "percentage": "7.30", "votes": "8,017"}, {"canCode": "125139", "bName": "BIAGTAN, LEOPOLDO (KBL)", "percentage": "7.93", "votes": "8,707"}, {"canCode": "125129", "bName": "CALIMLIM, WILFREDO (NPC)", "percentage": "4.97", "votes": "5,454"}, {"canCode": "125140", "bName": "CASILANG, DODONG (KBL)", "percentage": "4.20", "votes": "4,617"}, {"canCode": "125130", "bName": "DE VERA, LUIGI (NPC)", "percentage": "8.03", "votes": "8,819"}, {"canCode": "125135", "bName": "EDEN, MAMERTO JR. (NPC)", "percentage": "6.82", "votes": "7,485"}, {"canCode": "125137", "bName": "ESTAYO, ROMULO (IND)", "percentage": "3.24", "votes": "3,557"}, {"canCode": "125141", "bName": "FERNANDEZ, ALFREDO (KBL)", "percentage": "4.54", "votes": "4,987"}, {"canCode": "125138", "bName": "PARAGAS, ROMY (LP)", "percentage": "2.53", "votes": "2,781"}, {"canCode": "125136", "bName": "PENULIAR, DOOY (NPC)", "percentage": "9.31", "votes": "10,224"}, {"canCode": "125133", "bName": "PERIA, VIVIEN (NPC)", "percentage": "8.11", "votes": "8,908"}, {"canCode": "125142", "bName": "SISON, MAMERTO (KBL)", "percentage": "3.30", "votes": "3,629"}, {"canCode": "125143", "bName": "TAMAYO, DACK (KBL)", "percentage": "8.04", "votes": "8,823"}, {"canCode": "125144", "bName": "TAMAYO, MALOU (KBL)", "percentage": "3.25", "votes": "3,567"}, {"canCode": "125131", "bName": "VISPERAS, ALLAN (NPC)", "percentage": "5.69", "votes": "6,246"}], "code": "16194", "stats": {"transmission": "100.00", "ballots": {"rows": [{"value": "17,455", "label": "ballots.total"}]}, "regionInfo": {"rows": [{"value": "33", "label": "tally.total.4"}, {"value": "33", "label": "tally.reported.4"}]}, "voters": {"rows": [{"value": "20,694", "label": "voters.registered"}, {"value": "84.34%", "label": "voters.turn.out"}]}}, "name": "MEMBER, SANGGUNIANG BAYAN PANGASINAN - MAPANDAN  - LONE DIST", "cClass": "24"}