{"results": [{"canCode": "90098", "bName": "ALANO, YUSOP (NPC)", "percentage": "93.78", "votes": "4,694"}, {"canCode": "90097", "bName": "ESPITAL, GALIB (IND)", "percentage": "0.00", "votes": "0"}, {"canCode": "90099", "bName": "MUSARIN, MUSLIMIN (NP)", "percentage": "0.00", "votes": "0"}, {"canCode": "90096", "bName": "SAKKALAHUL, KEEMHAR JAY (LP)", "percentage": "6.21", "votes": "311"}], "code": "11500", "stats": {"transmission": "100.00", "ballots": {"rows": [{"value": "5,278", "label": "ballots.total"}]}, "regionInfo": {"rows": [{"value": "11", "label": "tally.total.4"}, {"value": "11", "label": "tally.reported.4"}]}, "voters": {"rows": [{"value": "5,349", "label": "voters.registered"}, {"value": "98.67%", "label": "voters.turn.out"}]}}, "name": "PROVINCIAL VICE-GOVERNOR BASILAN", "cClass": "10"}