{"results": [{"canCode": "96700", "bName": "ABAS, REYNALDO JR (IND)", "percentage": "0.25", "votes": "551"}, {"canCode": "96699", "bName": "FRESNEDI, JAIME (LP)", "percentage": "58.27", "votes": "125,128"}, {"canCode": "96701", "bName": "MARMETO, OSCAR (IND)", "percentage": "0.14", "votes": "316"}, {"canCode": "96697", "bName": "SAN PEDRO, ALDRIN (UNA)", "percentage": "31.77", "votes": "68,241"}, {"canCode": "96698", "bName": "SIMUNDAC, TEMY (NPC)", "percentage": "9.54", "votes": "20,496"}], "code": "13348", "stats": {"transmission": "100.00", "ballots": {"rows": [{"value": "224,446", "label": "ballots.total"}]}, "regionInfo": {"rows": [{"value": "427", "label": "tally.total.4"}, {"value": "427", "label": "tally.reported.4"}]}, "voters": {"rows": [{"value": "309,595", "label": "voters.registered"}, {"value": "72.49%", "label": "voters.turn.out"}]}}, "name": "MAYOR NCR - CITY OF MUNTINLUPA", "cClass": "18"}