{"results": [{"canCode": "89804", "bName": "ALBANI, SHARIFF (IND)", "percentage": "0.11", "votes": "236"}, {"canCode": "89805", "bName": "ALI, ALDIN (WPPPMM)", "percentage": "0.08", "votes": "179"}, {"canCode": "89798", "bName": "ALUNAN, RAFFY (IND)", "percentage": "0.44", "votes": "914"}, {"canCode": "89777", "bName": "AMBOLODTO, INA (LP)", "percentage": "0.13", "votes": "282"}, {"canCode": "89761", "bName": "ARQUIZA, GODOFREDO (IND)", "percentage": "0.14", "votes": "291"}, {"canCode": "89787", "bName": "BALIGOD, LEVITO (IND)", "percentage": "0.10", "votes": "219"}, {"canCode": "89796", "bName": "BELGICA, GRECO (IND)", "percentage": "0.36", "votes": "735"}, {"canCode": "89791", "bName": "BELLO, WALDEN (IND)", "percentage": "0.43", "votes": "891"}, {"canCode": "89776", "bName": "CAM, SANDRA (PMP)", "percentage": "0.14", "votes": "304"}, {"canCode": "89759", "bName": "CHAVEZ, MEL (WPPPMM)", "percentage": "0.57", "votes": "1,175"}, {"canCode": "89758", "bName": "COLMENARES, NERI (MKBYN)", "percentage": "2.82", "votes": "5,763"}, {"canCode": "89781", "bName": "DE LIMA, LEILA (LP)", "percentage": "4.44", "votes": "9,075"}, {"canCode": "89795", "bName": "DOMAGOSO, ISKO MORENO (PMP)", "percentage": "3.47", "votes": "7,086"}, {"canCode": "89803", "bName": "DORONA, RAY (IND)", "percentage": "0.19", "votes": "394"}, {"canCode": "89771", "bName": "DRILON, FRANK (LP)", "percentage": "5.83", "votes": "11,901"}, {"canCode": "89802", "bName": "GADON, LARRY (KBL)", "percentage": "0.59", "votes": "1,216"}, {"canCode": "89774", "bName": "GATCHALIAN, WIN (NPC)", "percentage": "5.35", "votes": "10,922"}, {"canCode": "89794", "bName": "GORDON, DICK (IND)", "percentage": "5.42", "votes": "11,055"}, {"canCode": "89782", "bName": "GUINGONA, TG (LP)", "percentage": "2.60", "votes": "5,315"}, {"canCode": "89766", "bName": "HONTIVEROS, RISA (AKBYN)", "percentage": "6.07", "votes": "12,389"}, {"canCode": "89800", "bName": "KABALU, EID (IND)", "percentage": "0.06", "votes": "134"}, {"canCode": "89779", "bName": "KAPUNAN, ATTY. LORNA (AKSYON)", "percentage": "0.47", "votes": "975"}, {"canCode": "89767", "bName": "KIRAM, PRINCESS JACEL (UNA)", "percentage": "0.33", "votes": "677"}, {"canCode": "89765", "bName": "LACSAMANA, ALMA MORENO (UNA)", "percentage": "1.29", "votes": "2,644"}, {"canCode": "89757", "bName": "LACSON, PANFILO PING (IND)", "percentage": "5.80", "votes": "11,835"}, {"canCode": "89786", "bName": "LANGIT, REY (UNA)", "percentage": "0.99", "votes": "2,029"}, {"canCode": "89768", "bName": "LAPID, MARK (AKSYON)", "percentage": "1.91", "votes": "3,915"}, {"canCode": "89797", "bName": "LIBAN, DANTE (IND)", "percentage": "0.10", "votes": "222"}, {"canCode": "89763", "bName": "MAGANTO, ROMEO (LAKAS)", "percentage": "0.26", "votes": "531"}, {"canCode": "89789", "bName": "MANZANO, EDU (IND)", "percentage": "1.70", "votes": "3,468"}, {"canCode": "89778", "bName": "MONTANO, ALLAN (UNA)", "percentage": "0.44", "votes": "915"}, {"canCode": "89801", "bName": "MONTA\u00d1O, MON (IND)", "percentage": "0.18", "votes": "374"}, {"canCode": "89784", "bName": "NAPE\u00d1AS, GETULIO (UNA)", "percentage": "0.62", "votes": "1,270"}, {"canCode": "89785", "bName": "OPLE, SUSAN (NP)", "percentage": "0.66", "votes": "1,357"}, {"canCode": "89783", "bName": "OSME\u00d1A, SERGIO III (IND)", "percentage": "3.94", "votes": "8,056"}, {"canCode": "89792", "bName": "PACQUIAO, MANNY (UNA)", "percentage": "4.24", "votes": "8,664"}, {"canCode": "89780", "bName": "PAEZ, MR. COOP (IND)", "percentage": "0.10", "votes": "204"}, {"canCode": "89762", "bName": "PAGDILAO, SAMUEL (IND)", "percentage": "0.34", "votes": "702"}, {"canCode": "89793", "bName": "PALPARAN, JOVITO JR. (IND)", "percentage": "0.24", "votes": "495"}, {"canCode": "89770", "bName": "PANGILINAN, KIKO (LP)", "percentage": "5.11", "votes": "10,428"}, {"canCode": "89788", "bName": "PETILLA, CARLOS JERICHO (LP)", "percentage": "1.71", "votes": "3,491"}, {"canCode": "89773", "bName": "RECTO, RALPH (LP)", "percentage": "4.78", "votes": "9,761"}, {"canCode": "89760", "bName": "ROMUALDEZ, MARTIN (LAKAS)", "percentage": "4.04", "votes": "8,240"}, {"canCode": "89772", "bName": "ROMULO, ROMAN (IND)", "percentage": "1.38", "votes": "2,831"}, {"canCode": "89799", "bName": "SANTIAGO, DIONISIO (IND)", "percentage": "0.34", "votes": "705"}, {"canCode": "89775", "bName": "SOTTO, VICENTE (NPC)", "percentage": "5.70", "votes": "11,634"}, {"canCode": "89769", "bName": "TOLENTINO, FRANCIS (IND)", "percentage": "3.75", "votes": "7,661"}, {"canCode": "89806", "bName": "VALEROSO, DIOSDADO (IND)", "percentage": "0.12", "votes": "255"}, {"canCode": "89790", "bName": "VILLANUEVA, JOEL TESDAMAN (LP)", "percentage": "5.45", "votes": "11,119"}, {"canCode": "89764", "bName": "ZUBIRI, MIGZ (IND)", "percentage": "4.42", "votes": "9,019"}], "code": "11163", "stats": {"transmission": "100.00", "ballots": {"rows": [{"value": "26,152", "label": "ballots.total"}]}, "regionInfo": {"rows": [{"value": "62", "label": "tally.total.4"}, {"value": "62", "label": "tally.reported.4"}]}, "voters": {"rows": [{"value": "30,713", "label": "voters.registered"}, {"value": "85.14%", "label": "voters.turn.out"}]}}, "name": "SENATOR PHILIPPINES", "cClass": "3"}