{"results": [{"canCode": "98893", "bName": "MUSTAPHA, DATUTATO (LP)", "percentage": "91.07", "votes": "7,749"}, {"canCode": "98894", "bName": "SINSUAT, ALAMABI (UNA)", "percentage": "8.92", "votes": "759"}], "code": "14291", "stats": {"transmission": "100.00", "ballots": {"rows": [{"value": "8,846", "label": "ballots.total"}]}, "regionInfo": {"rows": [{"value": "20", "label": "tally.total.4"}, {"value": "20", "label": "tally.reported.4"}]}, "voters": {"rows": [{"value": "9,247", "label": "voters.registered"}, {"value": "95.66%", "label": "voters.turn.out"}]}}, "name": "VICE-MAYOR MAGUINDANAO - DATU BLAH T. SINSUAT", "cClass": "19"}