{"name": "ALFONSO", "level": 4, "url": "data/regions/2101.json", "sitePath": "0/4A/2100/2101", "isFinalLevel": false, "subRegions": {"2101019": {"categoryName": "Barangay", "parentCustomCode": "2101", "level": 5, "url": "data/regions/2101019.json", "parentName": "ALFONSO", "isFinalLevel": true, "parentCategoryName": "City/Municipality", "customCode": "2101019", "name": "SULSUGIN"}, "2101027": {"categoryName": "Barangay", "parentCustomCode": "2101", "level": 5, "url": "data/regions/2101027.json", "parentName": "ALFONSO", "isFinalLevel": true, "parentCategoryName": "City/Municipality", "customCode": "2101027", "name": "ESPERANZA ILAYA"}, "2101018": {"categoryName": "Barangay", "parentCustomCode": "2101", "level": 5, "url": "data/regions/2101018.json", "parentName": "ALFONSO", "isFinalLevel": true, "parentCategoryName": "City/Municipality", "customCode": "2101018", "name": "SINALIW NA MUNTI"}, "2101030": {"categoryName": "Barangay", "parentCustomCode": "2101", "level": 5, "url": "data/regions/2101030.json", "parentName": "ALFONSO", "isFinalLevel": true, "parentCategoryName": "City/Municipality", "customCode": "2101030", "name": "MANGAS II"}, "2101031": {"categoryName": "Barangay", "parentCustomCode": "2101", "level": 5, "url": "data/regions/2101031.json", "parentName": "ALFONSO", "isFinalLevel": true, "parentCategoryName": "City/Municipality", "customCode": "2101031", "name": "MARAHAN II"}, "2101032": {"categoryName": "Barangay", "parentCustomCode": "2101", "level": 5, "url": "data/regions/2101032.json", "parentName": "ALFONSO", "isFinalLevel": true, "parentCategoryName": "City/Municipality", "customCode": "2101032", "name": "MATAGBAK II"}, "2101033": {"categoryName": "Barangay", "parentCustomCode": "2101", "level": 5, "url": "data/regions/2101033.json", "parentName": "ALFONSO", "isFinalLevel": true, "parentCategoryName": "City/Municipality", "customCode": "2101033", "name": "SANTA TERESA"}, "2101012": {"categoryName": "Barangay", "parentCustomCode": "2101", "level": 5, "url": "data/regions/2101012.json", "parentName": "ALFONSO", "isFinalLevel": true, "parentCategoryName": "City/Municipality", "customCode": "2101012", "name": "MARAHAN I"}, "2101013": {"categoryName": "Barangay", "parentCustomCode": "2101", "level": 5, "url": "data/regions/2101013.json", "parentName": "ALFONSO", "isFinalLevel": true, "parentCategoryName": "City/Municipality", "customCode": "2101013", "name": "MATAGBAK I"}, "2101010": {"categoryName": "Barangay", "parentCustomCode": "2101", "level": 5, "url": "data/regions/2101010.json", "parentName": "ALFONSO", "isFinalLevel": true, "parentCategoryName": "City/Municipality", "customCode": "2101010", "name": "LUKSUHIN"}, "2101011": {"categoryName": "Barangay", "parentCustomCode": "2101", "level": 5, "url": "data/regions/2101011.json", "parentName": "ALFONSO", "isFinalLevel": true, "parentCategoryName": "City/Municipality", "customCode": "2101011", "name": "MANGAS I"}, "2101016": {"categoryName": "Barangay", "parentCustomCode": "2101", "level": 5, "url": "data/regions/2101016.json", "parentName": "ALFONSO", "isFinalLevel": true, "parentCategoryName": "City/Municipality", "customCode": "2101016", "name": "SIKAT"}, "2101017": {"categoryName": "Barangay", "parentCustomCode": "2101", "level": 5, "url": "data/regions/2101017.json", "parentName": "ALFONSO", "isFinalLevel": true, "parentCategoryName": "City/Municipality", "customCode": "2101017", "name": "SINALIW MALAKI"}, "2101014": {"categoryName": "Barangay", "parentCustomCode": "2101", "level": 5, "url": "data/regions/2101014.json", "parentName": "ALFONSO", "isFinalLevel": true, "parentCategoryName": "City/Municipality", "customCode": "2101014", "name": "PAJO"}, "2101026": {"categoryName": "Barangay", "parentCustomCode": "2101", "level": 5, "url": "data/regions/2101026.json", "parentName": "ALFONSO", "isFinalLevel": true, "parentCategoryName": "City/Municipality", "customCode": "2101026", "name": "BILOG"}, "2101029": {"categoryName": "Barangay", "parentCustomCode": "2101", "level": 5, "url": "data/regions/2101029.json", "parentName": "ALFONSO", "isFinalLevel": true, "parentCategoryName": "City/Municipality", "customCode": "2101029", "name": "KAYTITINGA III"}, "2101006": {"categoryName": "Barangay", "parentCustomCode": "2101", "level": 5, "url": "data/regions/2101006.json", "parentName": "ALFONSO", "isFinalLevel": true, "parentCategoryName": "City/Municipality", "customCode": "2101006", "name": "BARANGAY V (POB.)"}, "2101023": {"categoryName": "Barangay", "parentCustomCode": "2101", "level": 5, "url": "data/regions/2101023.json", "parentName": "ALFONSO", "isFinalLevel": true, "parentCategoryName": "City/Municipality", "customCode": "2101023", "name": "KAYSUYO"}, "2101022": {"categoryName": "Barangay", "parentCustomCode": "2101", "level": 5, "url": "data/regions/2101022.json", "parentName": "ALFONSO", "isFinalLevel": true, "parentCategoryName": "City/Municipality", "customCode": "2101022", "name": "UPLI"}, "2101021": {"categoryName": "Barangay", "parentCustomCode": "2101", "level": 5, "url": "data/regions/2101021.json", "parentName": "ALFONSO", "isFinalLevel": true, "parentCategoryName": "City/Municipality", "customCode": "2101021", "name": "TAYWANAK ILAYA"}, "2101020": {"categoryName": "Barangay", "parentCustomCode": "2101", "level": 5, "url": "data/regions/2101020.json", "parentName": "ALFONSO", "isFinalLevel": true, "parentCategoryName": "City/Municipality", "customCode": "2101020", "name": "TAYWANAK IBABA"}, "2101009": {"categoryName": "Barangay", "parentCustomCode": "2101", "level": 5, "url": "data/regions/2101009.json", "parentName": "ALFONSO", "isFinalLevel": true, "parentCategoryName": "City/Municipality", "customCode": "2101009", "name": "KAYTITINGA I"}, "2101008": {"categoryName": "Barangay", "parentCustomCode": "2101", "level": 5, "url": "data/regions/2101008.json", "parentName": "ALFONSO", "isFinalLevel": true, "parentCategoryName": "City/Municipality", "customCode": "2101008", "name": "ESPERANZA IBABA"}, "2101025": {"categoryName": "Barangay", "parentCustomCode": "2101", "level": 5, "url": "data/regions/2101025.json", "parentName": "ALFONSO", "isFinalLevel": true, "parentCategoryName": "City/Municipality", "customCode": "2101025", "name": "PALUMLUM"}, "2101024": {"categoryName": "Barangay", "parentCustomCode": "2101", "level": 5, "url": "data/regions/2101024.json", "parentName": "ALFONSO", "isFinalLevel": true, "parentCategoryName": "City/Municipality", "customCode": "2101024", "name": "LUKSUHIN ILAYA"}, "2101005": {"categoryName": "Barangay", "parentCustomCode": "2101", "level": 5, "url": "data/regions/2101005.json", "parentName": "ALFONSO", "isFinalLevel": true, "parentCategoryName": "City/Municipality", "customCode": "2101005", "name": "BARANGAY IV (POB.)"}, "2101004": {"categoryName": "Barangay", "parentCustomCode": "2101", "level": 5, "url": "data/regions/2101004.json", "parentName": "ALFONSO", "isFinalLevel": true, "parentCategoryName": "City/Municipality", "customCode": "2101004", "name": "BARANGAY III (POB.)"}, "2101007": {"categoryName": "Barangay", "parentCustomCode": "2101", "level": 5, "url": "data/regions/2101007.json", "parentName": "ALFONSO", "isFinalLevel": true, "parentCategoryName": "City/Municipality", "customCode": "2101007", "name": "BUCK ESTATE"}, "2101028": {"categoryName": "Barangay", "parentCustomCode": "2101", "level": 5, "url": "data/regions/2101028.json", "parentName": "ALFONSO", "isFinalLevel": true, "parentCategoryName": "City/Municipality", "customCode": "2101028", "name": "KAYTITINGA II"}, "2101001": {"categoryName": "Barangay", "parentCustomCode": "2101", "level": 5, "url": "data/regions/2101001.json", "parentName": "ALFONSO", "isFinalLevel": true, "parentCategoryName": "City/Municipality", "customCode": "2101001", "name": "AMUYONG"}, "2101003": {"categoryName": "Barangay", "parentCustomCode": "2101", "level": 5, "url": "data/regions/2101003.json", "parentName": "ALFONSO", "isFinalLevel": true, "parentCategoryName": "City/Municipality", "customCode": "2101003", "name": "BARANGAY II (POB.)"}, "2101002": {"categoryName": "Barangay", "parentCustomCode": "2101", "level": 5, "url": "data/regions/2101002.json", "parentName": "ALFONSO", "isFinalLevel": true, "parentCategoryName": "City/Municipality", "customCode": "2101002", "name": "BARANGAY I (POB.)"}}, "parentRegionCC": "2100", "contests": [{"url": "tallies/288/288722/11161.json", "code": "11161", "customCode": "00199009", "cClass": "1"}, {"url": "tallies/288/288722/11162.json", "code": "11162", "customCode": "00299009", "cClass": "2"}, {"url": "tallies/288/288722/11163.json", "code": "11163", "customCode": "00399009", "cClass": "3"}, {"url": "tallies/288/288722/11164.json", "code": "11164", "customCode": "01199009", "cClass": "4"}, {"url": "tallies/288/288722/11219.json", "code": "11219", "customCode": "00721007", "cClass": "5"}, {"url": "tallies/288/288722/11433.json", "code": "11433", "customCode": "00421009", "cClass": "9"}, {"url": "tallies/288/288722/11514.json", "code": "11514", "customCode": "00521009", "cClass": "10"}, {"url": "tallies/288/288722/11599.json", "code": "11599", "customCode": "00621007", "cClass": "12"}, {"url": "tallies/288/288722/12183.json", "code": "12183", "customCode": "00821019", "cClass": "18"}, {"url": "tallies/288/288722/13817.json", "code": "13817", "customCode": "00921019", "cClass": "19"}, {"url": "tallies/288/288722/15472.json", "code": "15472", "customCode": "01021019", "cClass": "24"}], "customCode": "2101", "categoryName": "City/Municipality"}