{"results": [{"canCode": "89946", "bName": "FALCONE, BAL (IND)", "percentage": "4.60", "votes": "402"}, {"canCode": "89945", "bName": "NIELO, PHILIP (IND)", "percentage": "2.32", "votes": "203"}, {"canCode": "89944", "bName": "PETILLA, LEOPOLDO DOMINICO (LP)", "percentage": "93.07", "votes": "8,127"}], "code": "11449", "stats": {"transmission": "100.00", "ballots": {"rows": [{"value": "16,443", "label": "ballots.total"}]}, "regionInfo": {"rows": [{"value": "36", "label": "tally.total.4"}, {"value": "36", "label": "tally.reported.4"}]}, "voters": {"rows": [{"value": "19,727", "label": "voters.registered"}, {"value": "83.35%", "label": "voters.turn.out"}]}}, "name": "PROVINCIAL GOVERNOR LEYTE", "cClass": "9"}