{"results": [{"canCode": "92515", "bName": "GONZALES, AURELIO JR. (NPC)", "percentage": "50.92", "votes": "16,225"}, {"canCode": "92514", "bName": "QUIWA, POL (IND)", "percentage": "0.89", "votes": "284"}, {"canCode": "92517", "bName": "RODRIGUEZ, OSCAR (LP)", "percentage": "47.33", "votes": "15,082"}, {"canCode": "92516", "bName": "SANTOS, AMADO (IND)", "percentage": "0.84", "votes": "269"}], "code": "11319", "stats": {"transmission": "100.00", "ballots": {"rows": [{"value": "36,599", "label": "ballots.total"}]}, "regionInfo": {"rows": [{"value": "71", "label": "tally.total.4"}, {"value": "71", "label": "tally.reported.4"}]}, "voters": {"rows": [{"value": "43,843", "label": "voters.registered"}, {"value": "83.47%", "label": "voters.turn.out"}]}}, "name": "MEMBER, HOUSE OF REPRESENTATIVES PAMPANGA - THIRD LEGDIST", "cClass": "5"}