{"results": [{"canCode": "96514", "bName": "ACERON, BILLY (IND)", "percentage": "38.40", "votes": "6,851"}, {"canCode": "96511", "bName": "ALTARES, SERGIO (IND)", "percentage": "1.86", "votes": "332"}, {"canCode": "96512", "bName": "AMITA, JOEL (IND)", "percentage": "21.73", "votes": "3,877"}, {"canCode": "96513", "bName": "AMOG, MELCHOR (SZP)", "percentage": "28.41", "votes": "5,070"}, {"canCode": "96515", "bName": "GUATLO, ROSIE (LP)", "percentage": "9.59", "votes": "1,711"}], "code": "13275", "stats": {"transmission": "97.61", "ballots": {"rows": [{"value": "18,661", "label": "ballots.total"}]}, "regionInfo": {"rows": [{"value": "42", "label": "tally.total.4"}, {"value": "41", "label": "tally.reported.4"}]}, "voters": {"rows": [{"value": "23,107", "label": "voters.registered"}, {"value": "80.75%", "label": "voters.turn.out"}]}}, "name": "MAYOR ZAMBALES - PALAUIG", "cClass": "18"}