{"results": [{"canCode": "92199", "bName": "TALLADO, JOSEFINA (NPC)", "percentage": "41.59", "votes": "5,674"}, {"canCode": "92198", "bName": "UNICO, KUYA JOJO (LP)", "percentage": "58.40", "votes": "7,968"}], "code": "11202", "stats": {"transmission": "100.00", "ballots": {"rows": [{"value": "15,019", "label": "ballots.total"}]}, "regionInfo": {"rows": [{"value": "33", "label": "tally.total.4"}, {"value": "33", "label": "tally.reported.4"}]}, "voters": {"rows": [{"value": "17,754", "label": "voters.registered"}, {"value": "84.59%", "label": "voters.turn.out"}]}}, "name": "MEMBER, HOUSE OF REPRESENTATIVES CAMARINES NORTE - FIRST LEGDIST", "cClass": "5"}