{"results": [{"canCode": "118906", "bName": "ALMOSERA, ROSIE (NUP)", "percentage": "6.17", "votes": "5,654"}, {"canCode": "118909", "bName": "ANABE, JOLLY (NUP)", "percentage": "7.87", "votes": "7,208"}, {"canCode": "118913", "bName": "BARTOLAY, JIMSON (LP)", "percentage": "6.28", "votes": "5,754"}, {"canCode": "118908", "bName": "BELMES, LAMBI (NUP)", "percentage": "4.38", "votes": "4,014"}, {"canCode": "118916", "bName": "CANTORIA, EFREN (LP)", "percentage": "4.00", "votes": "3,667"}, {"canCode": "118914", "bName": "DEINLA, ROBERT (LP)", "percentage": "3.75", "votes": "3,441"}, {"canCode": "118918", "bName": "DELAVIN, JOHNNY (LP)", "percentage": "2.25", "votes": "2,063"}, {"canCode": "118917", "bName": "DELOS SANTOS, EDDIE (LP)", "percentage": "9.08", "votes": "8,318"}, {"canCode": "118904", "bName": "ESPINOSA, KAP JEROL (NUP)", "percentage": "8.61", "votes": "7,884"}, {"canCode": "118915", "bName": "ESPINOSA, TOKOY (LP)", "percentage": "8.25", "votes": "7,562"}, {"canCode": "118905", "bName": "ESPLANA, NONITA (NUP)", "percentage": "5.68", "votes": "5,204"}, {"canCode": "118907", "bName": "LAILA, VILING (NUP)", "percentage": "5.45", "votes": "4,997"}, {"canCode": "118910", "bName": "LIQUE, PANONG (NUP)", "percentage": "6.25", "votes": "5,730"}, {"canCode": "118911", "bName": "REAL, TARA ANNE (LP)", "percentage": "8.39", "votes": "7,687"}, {"canCode": "118912", "bName": "REJUSO, ANDRES (LP)", "percentage": "8.38", "votes": "7,679"}, {"canCode": "118903", "bName": "VILLAMOR, WAREN (NUP)", "percentage": "5.13", "votes": "4,699"}], "code": "15931", "stats": {"transmission": "100.00", "ballots": {"rows": [{"value": "15,182", "label": "ballots.total"}]}, "regionInfo": {"rows": [{"value": "34", "label": "tally.total.4"}, {"value": "34", "label": "tally.reported.4"}]}, "voters": {"rows": [{"value": "17,795", "label": "voters.registered"}, {"value": "85.31%", "label": "voters.turn.out"}]}}, "name": "MEMBER, SANGGUNIANG BAYAN MASBATE - SAN JACINTO   - LONE DIST", "cClass": "24"}