{"results": [{"canCode": "92330", "bName": "DUMPIT, TOMAS (NUP)", "percentage": "18.97", "votes": "4,306"}, {"canCode": "92331", "bName": "ERIGUEL, SANDRA (NPC)", "percentage": "81.02", "votes": "18,388"}], "code": "11256", "stats": {"transmission": "100.00", "ballots": {"rows": [{"value": "26,254", "label": "ballots.total"}]}, "regionInfo": {"rows": [{"value": "55", "label": "tally.total.4"}, {"value": "55", "label": "tally.reported.4"}]}, "voters": {"rows": [{"value": "30,817", "label": "voters.registered"}, {"value": "85.19%", "label": "voters.turn.out"}]}}, "name": "MEMBER, HOUSE OF REPRESENTATIVES LA UNION - SECOND LEGDIST", "cClass": "5"}