{"results": [{"canCode": "91220", "bName": "DECINA, TITO (NUP)", "percentage": "11.28", "votes": "56,361"}, {"canCode": "91222", "bName": "LUANSING, MENA (IND)", "percentage": "16.07", "votes": "80,297"}, {"canCode": "91224", "bName": "NAVARRO, DAN (IND)", "percentage": "12.85", "votes": "64,231"}, {"canCode": "91217", "bName": "NERI, SIMPLICIA (NUP)", "percentage": "8.33", "votes": "41,628"}, {"canCode": "91218", "bName": "OLEGARIO, GERARD (NUP)", "percentage": "11.09", "votes": "55,418"}, {"canCode": "91219", "bName": "PAROJINOG, OCTAVIO JR. (NUP)", "percentage": "14.63", "votes": "73,098"}, {"canCode": "91221", "bName": "ROA, MEMENG (NUP)", "percentage": "15.05", "votes": "75,213"}, {"canCode": "91223", "bName": "ROMERO, ROLAND (IND)", "percentage": "8.19", "votes": "40,923"}, {"canCode": "91216", "bName": "SALVANERA, BIANO (IND)", "percentage": "0.47", "votes": "2,381"}, {"canCode": "91225", "bName": "VILLANTES, DOMINADOR (IND)", "percentage": "0.54", "votes": "2,728"}, {"canCode": "91226", "bName": "ZAFRA, CARLO (IND)", "percentage": "1.44", "votes": "7,228"}], "code": "11758", "stats": {"transmission": "100.00", "ballots": {"rows": [{"value": "156,110", "label": "ballots.total"}]}, "regionInfo": {"rows": [{"value": "7", "label": "tally.total.3"}, {"value": "7", "label": "tally.reported.3"}]}, "voters": {"rows": [{"value": "192,259", "label": "voters.registered"}, {"value": "81.19%", "label": "voters.turn.out"}]}}, "name": "MEMBER, SANGGUNIANG PANLALAWIGAN MISAMIS OCCIDENTAL - SECOND PROVDIST", "cClass": "15"}