{"results": [{"canCode": "95321", "bName": "CATAMCO, CHERYL (LP)", "percentage": "57.36", "votes": "17,447"}, {"canCode": "95320", "bName": "MATALAM, ABDULLAH (NPC)", "percentage": "6.49", "votes": "1,974"}, {"canCode": "95323", "bName": "PRADO, NOVENH (KBL)", "percentage": "1.45", "votes": "442"}, {"canCode": "95319", "bName": "SINDAO, BOBBY (IND)", "percentage": "0.21", "votes": "65"}, {"canCode": "95322", "bName": "SONGCAYA, LEONARDO (NP)", "percentage": "34.47", "votes": "10,487"}], "code": "12810", "stats": {"transmission": "100.00", "ballots": {"rows": [{"value": "32,943", "label": "ballots.total"}]}, "regionInfo": {"rows": [{"value": "77", "label": "tally.total.4"}, {"value": "77", "label": "tally.reported.4"}]}, "voters": {"rows": [{"value": "42,599", "label": "voters.registered"}, {"value": "77.33%", "label": "voters.turn.out"}]}}, "name": "MAYOR COTABATO (NORTH COT.) - MATALAM", "cClass": "18"}