{"results": [{"canCode": "89745", "bName": "BINAY, JOJO (UNA)", "percentage": "3.40", "votes": "11,559"}, {"canCode": "89749", "bName": "DEFENSOR SANTIAGO, MIRIAM (PRP)", "percentage": "0.62", "votes": "2,135"}, {"canCode": "89750", "bName": "DUTERTE, RODY (PDPLBN)", "percentage": "57.62", "votes": "195,814"}, {"canCode": "89747", "bName": "POE, GRACE (IND)", "percentage": "15.85", "votes": "53,879"}, {"canCode": "89746", "bName": "ROXAS, MAR DAANG MATUWID (LP)", "percentage": "22.44", "votes": "76,267"}, {"canCode": "89748", "bName": "SE\u00d1ERES, ROY (WPPPMM)", "percentage": "0.04", "votes": "154"}], "code": "11161", "stats": {"transmission": "100.00", "ballots": {"rows": [{"value": "361,710", "label": "ballots.total"}]}, "regionInfo": {"rows": [{"value": "12", "label": "tally.total.3"}, {"value": "12", "label": "tally.reported.3"}]}, "voters": {"rows": [{"value": "411,961", "label": "voters.registered"}, {"value": "87.80%", "label": "voters.turn.out"}]}}, "name": "PRESIDENT PHILIPPINES", "cClass": "1"}