{"results": [{"canCode": "90111", "bName": "BALITE, DIONING (PDPLBN)", "percentage": "49.79", "votes": "8,996"}, {"canCode": "90112", "bName": "LIM, CONCEPCION (LP)", "percentage": "50.20", "votes": "9,069"}], "code": "11505", "stats": {"transmission": "100.00", "ballots": {"rows": [{"value": "23,142", "label": "ballots.total"}]}, "regionInfo": {"rows": [{"value": "39", "label": "tally.total.4"}, {"value": "39", "label": "tally.reported.4"}]}, "voters": {"rows": [{"value": "26,470", "label": "voters.registered"}, {"value": "87.42%", "label": "voters.turn.out"}]}}, "name": "PROVINCIAL VICE-GOVERNOR BOHOL", "cClass": "10"}