{"results": [{"canCode": "89756", "bName": "CAYETANO, ALAN PETER (IND)", "percentage": "6.66", "votes": "682"}, {"canCode": "89755", "bName": "ESCUDERO, CHIZ (IND)", "percentage": "15.32", "votes": "1,568"}, {"canCode": "89751", "bName": "HONASAN, GRINGO (UNA)", "percentage": "4.26", "votes": "436"}, {"canCode": "89752", "bName": "MARCOS, BONGBONG (IND)", "percentage": "40.95", "votes": "4,191"}, {"canCode": "89754", "bName": "ROBREDO, LENI DAANG MATUWID (LP)", "percentage": "30.27", "votes": "3,098"}, {"canCode": "89753", "bName": "TRILLANES, ANTONIO IV (IND)", "percentage": "2.52", "votes": "258"}], "code": "11162", "stats": {"transmission": "100.00", "ballots": {"rows": [{"value": "10,928", "label": "ballots.total"}]}, "regionInfo": {"rows": [{"value": "24", "label": "tally.total.4"}, {"value": "24", "label": "tally.reported.4"}]}, "voters": {"rows": [{"value": "13,579", "label": "voters.registered"}, {"value": "80.47%", "label": "voters.turn.out"}]}}, "name": "VICE-PRESIDENT PHILIPPINES", "cClass": "2"}