{"results": [{"canCode": "98987", "bName": "DUMANJUG, EVELYN (NP)", "percentage": "100.00", "votes": "13,004"}], "code": "14329", "stats": {"transmission": "97.43", "ballots": {"rows": [{"value": "16,615", "label": "ballots.total"}]}, "regionInfo": {"rows": [{"value": "39", "label": "tally.total.4"}, {"value": "38", "label": "tally.reported.4"}]}, "voters": {"rows": [{"value": "20,311", "label": "voters.registered"}, {"value": "81.80%", "label": "voters.turn.out"}]}}, "name": "VICE-MAYOR MISAMIS OCCIDENTAL - BONIFACIO", "cClass": "19"}