{"results": [{"canCode": "100574", "bName": "ESPA\u00d1OL, RONNEL (LP)", "percentage": "40.69", "votes": "13,582"}, {"canCode": "100571", "bName": "GRAFILO, CORAZON (PCM)", "percentage": "27.55", "votes": "9,197"}, {"canCode": "100573", "bName": "HERRERA, GOLDEN BOY (NPC)", "percentage": "25.46", "votes": "8,498"}, {"canCode": "100572", "bName": "SADAVAO, TUNGKO (IND)", "percentage": "6.28", "votes": "2,099"}], "code": "15008", "stats": {"transmission": "100.00", "ballots": {"rows": [{"value": "37,009", "label": "ballots.total"}]}, "regionInfo": {"rows": [{"value": "71", "label": "tally.total.4"}, {"value": "71", "label": "tally.reported.4"}]}, "voters": {"rows": [{"value": "45,780", "label": "voters.registered"}, {"value": "80.84%", "label": "voters.turn.out"}]}}, "name": "VICE-MAYOR SARANGANI - ALABEL", "cClass": "19"}