{"results": [{"canCode": "91592", "bName": "DORADO, FRED (NP)", "percentage": "19.97", "votes": "30,856"}, {"canCode": "91593", "bName": "FONDEVILLA, ANDREW (LP)", "percentage": "22.63", "votes": "34,968"}, {"canCode": "91596", "bName": "GALANGERA, BILLY (IND)", "percentage": "2.17", "votes": "3,362"}, {"canCode": "91590", "bName": "MARAVILLA, VENIZAR (NP)", "percentage": "19.69", "votes": "30,421"}, {"canCode": "91595", "bName": "MARIN, LUIS VIRGILIO (IND)", "percentage": "4.37", "votes": "6,760"}, {"canCode": "91594", "bName": "SUAREZ-FETESIO, ORLALYN (UNA)", "percentage": "7.54", "votes": "11,657"}, {"canCode": "91591", "bName": "YLAGAN, FELIX (LP)", "percentage": "23.59", "votes": "36,456"}], "code": "11704", "stats": {"transmission": "100.00", "ballots": {"rows": [{"value": "75,465", "label": "ballots.total"}]}, "regionInfo": {"rows": [{"value": "9", "label": "tally.total.3"}, {"value": "9", "label": "tally.reported.3"}]}, "voters": {"rows": [{"value": "91,661", "label": "voters.registered"}, {"value": "82.33%", "label": "voters.turn.out"}]}}, "name": "MEMBER, SANGGUNIANG PANLALAWIGAN ROMBLON - SECOND PROVDIST", "cClass": "14"}